easy_file/__init__.py
easy_file/easy_file.py
easy_file/py.typed
easy_file-0.4.1.dist-info/METADATA
easy_file-0.4.1.dist-info/WHEEL
easy_file-0.4.1.dist-info/licenses/LICENSE
easy_file-0.4.1.dist-info/RECORD
