Metadata-Version: 2.4
Name: easy_file
Version: 0.4.1
Summary: Files for humans.
Project-URL: Homepage, https://github.com/ruslan-rv-ua/easy_file
Project-URL: Repository, https://github.com/ruslan-rv-ua/easy_file
Project-URL: Issues, https://github.com/ruslan-rv-ua/easy_file/issues
Author-email: Ruslan Iskov <ruslan.rv.ua@gmail.com>
License: MIT
License-File: LICENSE
Keywords: file,json,pathlib,yaml
Classifier: Development Status :: 4 - Beta
Classifier: Intended Audience :: Developers
Classifier: License :: OSI Approved :: MIT License
Classifier: Natural Language :: English
Classifier: Programming Language :: Python :: 3
Classifier: Programming Language :: Python :: 3.12
Classifier: Programming Language :: Python :: 3.13
Classifier: Programming Language :: Python :: 3.14
Requires-Python: >=3.12
Requires-Dist: msgspec>=0.18.0
Provides-Extra: dev
Requires-Dist: mypy>=1.5.0; extra == 'dev'
Requires-Dist: pre-commit>=3.5.0; extra == 'dev'
Requires-Dist: pytest-asyncio>=0.21.0; extra == 'dev'
Requires-Dist: pytest-cov>=4.1.0; extra == 'dev'
Requires-Dist: pytest>=7.4.0; extra == 'dev'
Requires-Dist: ruff>=0.1.0; extra == 'dev'
